{
   "Description" : {
      "Id" : "movedef_mackie_MSK-9H",
      "Name" : "MovementCapabilitiesDef for Mackie MSK-9H",
      "Details" : "",
      "Icon" : ""
   },
   "MaxWalkDistance" : 95.0,
   "MaxSprintDistance" : 165.0,
   "WalkVelocity" : 20.0,
   "RunVelocity" : 28.0,
   "SprintVelocity" : 32.0,
   "LimpVelocity" : 8.0,
   "WalkAcceleration" : 10.0,
   "SprintAcceleration" : 15.0,
   "MaxRadialVelocity" : 15.0,
   "MaxRadialAcceleration" : 15.0,
   "MaxJumpVel" : 30.0,
   "MaxJumpAccel" : 15.0,
   "MaxJumpVerticalAccel" : 30.0
}
